LICENSE
MANIFEST.in
README.md
pyproject.toml
setup.py
multiqc_jupyterlab_helper/__init__.py
multiqc_jupyterlab_helper/__main__.py
multiqc_jupyterlab_helper/multiqc.py
multiqc_jupyterlab_helper.egg-info/PKG-INFO
multiqc_jupyterlab_helper.egg-info/SOURCES.txt
multiqc_jupyterlab_helper.egg-info/dependency_links.txt
multiqc_jupyterlab_helper.egg-info/entry_points.txt
multiqc_jupyterlab_helper.egg-info/not-zip-safe
multiqc_jupyterlab_helper.egg-info/requires.txt
multiqc_jupyterlab_helper.egg-info/top_level.txt
multiqc_jupyterlab_helper/modules/__init__.py
multiqc_jupyterlab_helper/modules/base_module.py
multiqc_jupyterlab_helper/modules/adapterRemoval/__init__.py
multiqc_jupyterlab_helper/modules/adapterRemoval/adapterRemoval.py
multiqc_jupyterlab_helper/modules/afterqc/__init__.py
multiqc_jupyterlab_helper/modules/afterqc/afterqc.py
multiqc_jupyterlab_helper/modules/bamtools/__init__.py
multiqc_jupyterlab_helper/modules/bamtools/bamtools.py
multiqc_jupyterlab_helper/modules/bamtools/stats.py
multiqc_jupyterlab_helper/modules/bbmap/__init__.py
multiqc_jupyterlab_helper/modules/bbmap/bbmap.py
multiqc_jupyterlab_helper/modules/bbmap/bbmap_filetypes.py
multiqc_jupyterlab_helper/modules/bbmap/plot_aqhist.py
multiqc_jupyterlab_helper/modules/bbmap/plot_basic_hist.py
multiqc_jupyterlab_helper/modules/bbmap/plot_bhist.py
multiqc_jupyterlab_helper/modules/bbmap/plot_bqhist.py
multiqc_jupyterlab_helper/modules/bbmap/plot_covhist.py
multiqc_jupyterlab_helper/modules/bbmap/plot_idhist.py
multiqc_jupyterlab_helper/modules/bbmap/plot_ihist.py
multiqc_jupyterlab_helper/modules/bbmap/plot_indelhist.py
multiqc_jupyterlab_helper/modules/bbmap/plot_mhist.py
multiqc_jupyterlab_helper/modules/bbmap/plot_qahist.py
multiqc_jupyterlab_helper/modules/bbmap/plot_qhist.py
multiqc_jupyterlab_helper/modules/bcftools/__init__.py
multiqc_jupyterlab_helper/modules/bcftools/bcftools.py
multiqc_jupyterlab_helper/modules/bcftools/stats.py
multiqc_jupyterlab_helper/modules/bcl2fastq/__init__.py
multiqc_jupyterlab_helper/modules/bcl2fastq/bcl2fastq.py
multiqc_jupyterlab_helper/modules/bclconvert/__init__.py
multiqc_jupyterlab_helper/modules/bclconvert/bclconvert.py
multiqc_jupyterlab_helper/modules/biobambam2/__init__.py
multiqc_jupyterlab_helper/modules/biobambam2/biobambam2.py
multiqc_jupyterlab_helper/modules/biobloomtools/__init__.py
